{
  "timestamp": "2026-05-18T12:45:37.181034+00:00",
  "indices": {
    "SP500": {
      "symbol": "SPY",
      "price": 740.08,
      "change_percent": 0.12
    },
    "NASDAQ": {
      "symbol": "QQQ",
      "price": 711.64,
      "change_percent": 0.38
    },
    "GOLD": {
      "symbol": "GLD",
      "price": 419.79,
      "change_percent": 0.6
    }
  },
  "crypto": {
    "BITCOIN": {
      "price": 77667,
      "change_pct": -0.9577703547813664
    },
    "ETHEREUM": {
      "price": 2153.34,
      "change_pct": -1.890355052797181
    },
    "SOLANA": {
      "price": 85.66,
      "change_pct": -1.412431720010959
    }
  },
  "status": "ok",
  "errors": []
}