{
  "timestamp": "2026-05-12T13:45:29.685305+00:00",
  "indices": {
    "SP500": {
      "symbol": "SPY",
      "price": 736.64,
      "change_percent": -0.36
    },
    "NASDAQ": {
      "symbol": "QQQ",
      "price": 709.52,
      "change_percent": -0.53
    },
    "GOLD": {
      "symbol": "GLD",
      "price": 431.57,
      "change_percent": -0.71
    }
  },
  "crypto": {
    "BITCOIN": {
      "price": 80759,
      "change_pct": -0.301029177217483
    },
    "ETHEREUM": {
      "price": 2280.09,
      "change_pct": -1.8425471645479414
    },
    "SOLANA": {
      "price": 95.04,
      "change_pct": 0.01811008828143564
    }
  },
  "status": "ok",
  "errors": []
}