{
  "timestamp": "2026-05-13T14:40:59.259359+00:00",
  "indices": {
    "SP500": {
      "symbol": "SPY",
      "price": 737.98,
      "change_percent": -0.03
    },
    "NASDAQ": {
      "symbol": "QQQ",
      "price": 708.74,
      "change_percent": 0.21
    },
    "GOLD": {
      "symbol": "GLD",
      "price": 430.35,
      "change_percent": -0.6
    }
  },
  "crypto": {
    "BITCOIN": {
      "price": 79754,
      "change_pct": -1.2758255761609911
    },
    "ETHEREUM": {
      "price": 2265.91,
      "change_pct": -0.5077788288996943
    },
    "SOLANA": {
      "price": 91.97,
      "change_pct": -3.2163136270923287
    }
  },
  "status": "ok",
  "errors": []
}