{
  "timestamp": "2026-05-04T13:31:01.551915+00:00",
  "indices": {
    "SP500": {
      "symbol": "SPY",
      "price": 719.86,
      "change_percent": -0.11
    },
    "NASDAQ": {
      "symbol": "QQQ",
      "price": 674.89,
      "change_percent": 0.11
    },
    "GOLD": {
      "symbol": "GLD",
      "price": 418.68,
      "change_percent": -1.06
    }
  },
  "crypto": {
    "BITCOIN": {
      "price": 78946,
      "change_pct": 0.38044899064092563
    },
    "ETHEREUM": {
      "price": 2338.19,
      "change_pct": 0.5424753945282733
    },
    "SOLANA": {
      "price": 84.08,
      "change_pct": -0.0027387281229383784
    }
  },
  "status": "ok",
  "errors": []
}