{
  "timestamp": "2026-05-19T17:50:32.588252+00:00",
  "indices": {
    "SP500": {
      "symbol": "SPY",
      "price": 736.73,
      "change_percent": -0.26
    },
    "NASDAQ": {
      "symbol": "QQQ",
      "price": 704.97,
      "change_percent": -0.13
    },
    "GOLD": {
      "symbol": "GLD",
      "price": 413.31,
      "change_percent": -1.22
    }
  },
  "crypto": {
    "BITCOIN": {
      "price": 76756,
      "change_pct": 0.14321559718567745
    },
    "ETHEREUM": {
      "price": 2113.35,
      "change_pct": 0.2835206743360819
    },
    "SOLANA": {
      "price": 84.47,
      "change_pct": 0.15892321305281343
    }
  },
  "status": "ok",
  "errors": []
}