{
  "timestamp": "2026-05-09T00:10:11.210685+00:00",
  "indices": {
    "SP500": {
      "symbol": "SPY",
      "price": 737.94,
      "change_percent": 0.06
    },
    "NASDAQ": {
      "symbol": "QQQ",
      "price": 712.18,
      "change_percent": 0.16
    },
    "GOLD": {
      "symbol": "GLD",
      "price": 432.94,
      "change_percent": -0.21
    }
  },
  "crypto": {
    "BITCOIN": {
      "price": 80145,
      "change_pct": 0.11070814322979611
    },
    "ETHEREUM": {
      "price": 2304.61,
      "change_pct": 0.5114257885518539
    },
    "SOLANA": {
      "price": 91.91,
      "change_pct": 3.7965965968312254
    }
  },
  "status": "ok",
  "errors": []
}