{
  "timestamp": "2026-05-08T03:41:02.982045+00:00",
  "indices": {
    "SP500": {
      "symbol": "SPY",
      "price": 731.58,
      "change_percent": -0.31
    },
    "NASDAQ": {
      "symbol": "QQQ",
      "price": 694.94,
      "change_percent": -0.12
    },
    "GOLD": {
      "symbol": "GLD",
      "price": 431.68,
      "change_percent": 0.17
    }
  },
  "crypto": {
    "BITCOIN": {
      "price": 79607,
      "change_pct": -1.685328119128434
    },
    "ETHEREUM": {
      "price": 2279.85,
      "change_pct": -1.8241138005039372
    },
    "SOLANA": {
      "price": 88.29,
      "change_pct": 0.43475375656392273
    }
  },
  "status": "ok",
  "errors": []
}