{
  "timestamp": "2026-05-07T19:25:38.296868+00:00",
  "indices": {
    "SP500": {
      "symbol": "SPY",
      "price": 730.13,
      "change_percent": -0.5
    },
    "NASDAQ": {
      "symbol": "QQQ",
      "price": 692.67,
      "change_percent": -0.45
    },
    "GOLD": {
      "symbol": "GLD",
      "price": 431.27,
      "change_percent": 0.07
    }
  },
  "crypto": {
    "BITCOIN": {
      "price": 79987,
      "change_pct": -1.6367113584118915
    },
    "ETHEREUM": {
      "price": 2291.83,
      "change_pct": -2.335407607337543
    },
    "SOLANA": {
      "price": 88.33,
      "change_pct": -0.9347381563572328
    }
  },
  "status": "ok",
  "errors": []
}