{
  "timestamp": "2026-05-06T15:55:40.822219+00:00",
  "indices": {
    "SP500": {
      "symbol": "SPY",
      "price": 731.87,
      "change_percent": 1.12
    },
    "NASDAQ": {
      "symbol": "QQQ",
      "price": 692.15,
      "change_percent": 1.55
    },
    "GOLD": {
      "symbol": "GLD",
      "price": 430.9,
      "change_percent": 3.02
    }
  },
  "crypto": {
    "BITCOIN": {
      "price": 81712,
      "change_pct": 0.20920191909923042
    },
    "ETHEREUM": {
      "price": 2359.25,
      "change_pct": -0.9728615929460467
    },
    "SOLANA": {
      "price": 88.95,
      "change_pct": 4.021571983928551
    }
  },
  "status": "ok",
  "errors": []
}