{
  "timestamp": "2026-05-04T18:00:36.181811+00:00",
  "indices": {
    "SP500": {
      "symbol": "SPY",
      "price": 718.41,
      "change_percent": -0.31
    },
    "NASDAQ": {
      "symbol": "QQQ",
      "price": 673.27,
      "change_percent": -0.13
    },
    "GOLD": {
      "symbol": "GLD",
      "price": 415.17,
      "change_percent": -1.89
    }
  },
  "crypto": {
    "BITCOIN": {
      "price": 80482,
      "change_pct": 2.2455396375523704
    },
    "ETHEREUM": {
      "price": 2373.85,
      "change_pct": 1.8335420806640368
    },
    "SOLANA": {
      "price": 85.04,
      "change_pct": 1.0170736150515018
    }
  },
  "status": "ok",
  "errors": []
}