{
  "timestamp": "2026-05-20T21:10:29.389999+00:00",
  "indices": {
    "SP500": {
      "symbol": "SPY",
      "price": 739.15,
      "change_percent": -0.28
    },
    "NASDAQ": {
      "symbol": "QQQ",
      "price": 710.01,
      "change_percent": -0.44
    },
    "GOLD": {
      "symbol": "GLD",
      "price": 416.5,
      "change_percent": -0.21
    }
  },
  "crypto": {
    "BITCOIN": {
      "price": 77652,
      "change_pct": 0.9689684938741172
    },
    "ETHEREUM": {
      "price": 2134.51,
      "change_pct": 0.9004069815048585
    },
    "SOLANA": {
      "price": 86.11,
      "change_pct": 2.094591943075908
    }
  },
  "status": "ok",
  "errors": []
}