{
  "timestamp": "2026-05-11T16:40:11.372127+00:00",
  "indices": {
    "SP500": {
      "symbol": "SPY",
      "price": 740.11,
      "change_percent": 0.34
    },
    "NASDAQ": {
      "symbol": "QQQ",
      "price": 713.5,
      "change_percent": 0.32
    },
    "GOLD": {
      "symbol": "GLD",
      "price": 433.39,
      "change_percent": -0.09
    }
  },
  "crypto": {
    "BITCOIN": {
      "price": 81823,
      "change_pct": 0.7079415465358418
    },
    "ETHEREUM": {
      "price": 2334.94,
      "change_pct": -0.4989285352824489
    },
    "SOLANA": {
      "price": 97.6,
      "change_pct": 3.2836132305578856
    }
  },
  "status": "ok",
  "errors": []
}