{
  "timestamp": "2026-05-06T14:00:44.300339+00:00",
  "indices": {
    "SP500": {
      "symbol": "SPY",
      "price": 729.72,
      "change_percent": 0.82
    },
    "NASDAQ": {
      "symbol": "QQQ",
      "price": 689.63,
      "change_percent": 1.18
    },
    "GOLD": {
      "symbol": "GLD",
      "price": 431.93,
      "change_percent": 3.27
    }
  },
  "crypto": {
    "BITCOIN": {
      "price": 81691,
      "change_pct": 0.4056225195000451
    },
    "ETHEREUM": {
      "price": 2369.26,
      "change_pct": -0.8350303839140198
    },
    "SOLANA": {
      "price": 88.34,
      "change_pct": 3.217389544395883
    }
  },
  "status": "ok",
  "errors": []
}