{
  "timestamp": "2026-05-07T11:05:46.738059+00:00",
  "indices": {
    "SP500": {
      "symbol": "SPY",
      "price": 734.92,
      "change_percent": 0.15
    },
    "NASDAQ": {
      "symbol": "QQQ",
      "price": 696.5,
      "change_percent": 0.1
    },
    "GOLD": {
      "symbol": "GLD",
      "price": 434.6,
      "change_percent": 0.84
    }
  },
  "crypto": {
    "BITCOIN": {
      "price": 80913,
      "change_pct": -1.832674554923516
    },
    "ETHEREUM": {
      "price": 2328.15,
      "change_pct": -3.3851274635340483
    },
    "SOLANA": {
      "price": 89.25,
      "change_pct": -0.14142941489174193
    }
  },
  "status": "ok",
  "errors": []
}