{
  "timestamp": "2026-05-08T13:40:34.932035+00:00",
  "indices": {
    "SP500": {
      "symbol": "SPY",
      "price": 734.85,
      "change_percent": 0.45
    },
    "NASDAQ": {
      "symbol": "QQQ",
      "price": 701.72,
      "change_percent": 0.98
    },
    "GOLD": {
      "symbol": "GLD",
      "price": 435.18,
      "change_percent": 0.81
    }
  },
  "crypto": {
    "BITCOIN": {
      "price": 79758,
      "change_pct": -1.0951820550903948
    },
    "ETHEREUM": {
      "price": 2275.1,
      "change_pct": -1.8026116830531256
    },
    "SOLANA": {
      "price": 88.36,
      "change_pct": -0.776508803690263
    }
  },
  "status": "ok",
  "errors": []
}