{
  "timestamp": "2026-05-18T14:55:53.936566+00:00",
  "indices": {
    "SP500": {
      "symbol": "SPY",
      "price": 738.29,
      "change_percent": -0.12
    },
    "NASDAQ": {
      "symbol": "QQQ",
      "price": 704.82,
      "change_percent": -0.58
    },
    "GOLD": {
      "symbol": "GLD",
      "price": 417.15,
      "change_percent": -0.03
    }
  },
  "crypto": {
    "BITCOIN": {
      "price": 76362,
      "change_pct": -2.1260703833452053
    },
    "ETHEREUM": {
      "price": 2109.01,
      "change_pct": -3.5205622983862845
    },
    "SOLANA": {
      "price": 83.91,
      "change_pct": -2.7722683895557965
    }
  },
  "status": "ok",
  "errors": []
}