{
  "timestamp": "2026-05-15T11:41:04.133529+00:00",
  "indices": {
    "SP500": {
      "symbol": "SPY",
      "price": 741.14,
      "change_percent": -0.94
    },
    "NASDAQ": {
      "symbol": "QQQ",
      "price": 710.13,
      "change_percent": -1.34
    },
    "GOLD": {
      "symbol": "GLD",
      "price": 418.06,
      "change_percent": -2.14
    }
  },
  "crypto": {
    "BITCOIN": {
      "price": 80594,
      "change_pct": 1.6901271232252848
    },
    "ETHEREUM": {
      "price": 2258.28,
      "change_pct": 0.2012504138263015
    },
    "SOLANA": {
      "price": 91.32,
      "change_pct": 0.7420454354590545
    }
  },
  "status": "ok",
  "errors": []
}