{
  "timestamp": "2026-05-07T21:40:56.216883+00:00",
  "indices": {
    "SP500": {
      "symbol": "SPY",
      "price": 729.49,
      "change_percent": -0.29
    },
    "NASDAQ": {
      "symbol": "QQQ",
      "price": 692.88,
      "change_percent": -0.3
    },
    "GOLD": {
      "symbol": "GLD",
      "price": 430.2,
      "change_percent": -0.35
    }
  },
  "crypto": {
    "BITCOIN": {
      "price": 79885,
      "change_pct": -2.077831144425031
    },
    "ETHEREUM": {
      "price": 2292.52,
      "change_pct": -2.6963834215943194
    },
    "SOLANA": {
      "price": 88.14,
      "change_pct": -1.5383223307123783
    }
  },
  "status": "ok",
  "errors": []
}