{
  "timestamp": "2026-05-08T17:25:49.999943+00:00",
  "indices": {
    "SP500": {
      "symbol": "SPY",
      "price": 737.82,
      "change_percent": 0.85
    },
    "NASDAQ": {
      "symbol": "QQQ",
      "price": 710.23,
      "change_percent": 2.2
    },
    "GOLD": {
      "symbol": "GLD",
      "price": 433.32,
      "change_percent": 0.38
    }
  },
  "crypto": {
    "BITCOIN": {
      "price": 79939,
      "change_pct": 0.3037099960741498
    },
    "ETHEREUM": {
      "price": 2297.83,
      "change_pct": 0.4089856083725443
    },
    "SOLANA": {
      "price": 89.97,
      "change_pct": 1.8032089353419762
    }
  },
  "status": "ok",
  "errors": []
}