{
  "timestamp": "2026-05-19T13:50:10.926376+00:00",
  "indices": {
    "SP500": {
      "symbol": "SPY",
      "price": 735.08,
      "change_percent": -0.48
    },
    "NASDAQ": {
      "symbol": "QQQ",
      "price": 702.91,
      "change_percent": -0.42
    },
    "GOLD": {
      "symbol": "GLD",
      "price": 411.33,
      "change_percent": -1.7
    }
  },
  "crypto": {
    "BITCOIN": {
      "price": 76827,
      "change_pct": -0.1096408981623822
    },
    "ETHEREUM": {
      "price": 2119.51,
      "change_pct": -0.50608942549566
    },
    "SOLANA": {
      "price": 84.67,
      "change_pct": -0.09950980315328425
    }
  },
  "status": "ok",
  "errors": []
}