{
  "timestamp": "2026-05-03T21:20:26.627289+00:00",
  "indices": {
    "SP500": {
      "symbol": "SPY",
      "price": 720.65,
      "change_percent": 0.28
    },
    "NASDAQ": {
      "symbol": "QQQ",
      "price": 674.15,
      "change_percent": 0.96
    },
    "GOLD": {
      "symbol": "GLD",
      "price": 423.18,
      "change_percent": -0.11
    }
  },
  "crypto": {
    "BITCOIN": {
      "price": 78965,
      "change_pct": 0.636291566638775
    },
    "ETHEREUM": {
      "price": 2331.24,
      "change_pct": 0.8336533390342491
    },
    "SOLANA": {
      "price": 84.4,
      "change_pct": 0.2166268447453329
    }
  },
  "status": "ok",
  "errors": []
}