{
  "timestamp": "2026-05-18T03:50:30.595381+00:00",
  "indices": {
    "SP500": {
      "symbol": "SPY",
      "price": 739.17,
      "change_percent": -1.2
    },
    "NASDAQ": {
      "symbol": "QQQ",
      "price": 708.93,
      "change_percent": -1.51
    },
    "GOLD": {
      "symbol": "GLD",
      "price": 417.29,
      "change_percent": -2.32
    }
  },
  "crypto": {
    "BITCOIN": {
      "price": 76923,
      "change_pct": -1.3755753539292308
    },
    "ETHEREUM": {
      "price": 2119.12,
      "change_pct": -2.8353015133551778
    },
    "SOLANA": {
      "price": 84.89,
      "change_pct": -1.8438688199143258
    }
  },
  "status": "ok",
  "errors": []
}