{
  "timestamp": "2026-05-07T08:05:59.058775+00:00",
  "indices": {
    "SP500": {
      "symbol": "SPY",
      "price": 735.81,
      "change_percent": 0.27
    },
    "NASDAQ": {
      "symbol": "QQQ",
      "price": 698.08,
      "change_percent": 0.33
    },
    "GOLD": {
      "symbol": "GLD",
      "price": 436.08,
      "change_percent": 1.19
    }
  },
  "crypto": {
    "BITCOIN": {
      "price": 81533,
      "change_pct": 0.08835989773229731
    },
    "ETHEREUM": {
      "price": 2345.37,
      "change_pct": -1.2373972457788969
    },
    "SOLANA": {
      "price": 90.11,
      "change_pct": 2.7387407906122543
    }
  },
  "status": "ok",
  "errors": []
}