{
  "timestamp": "2026-05-13T05:35:44.276329+00:00",
  "indices": {
    "SP500": {
      "symbol": "SPY",
      "price": 738.18,
      "change_percent": -0.15
    },
    "NASDAQ": {
      "symbol": "QQQ",
      "price": 707.24,
      "change_percent": -0.85
    },
    "GOLD": {
      "symbol": "GLD",
      "price": 432.93,
      "change_percent": -0.4
    }
  },
  "crypto": {
    "BITCOIN": {
      "price": 81059,
      "change_pct": -0.18010290866874173
    },
    "ETHEREUM": {
      "price": 2299.26,
      "change_pct": -0.49222357070908707
    },
    "SOLANA": {
      "price": 95.36,
      "change_pct": -1.2911303219728691
    }
  },
  "status": "ok",
  "errors": []
}