{
  "timestamp": "2026-05-13T08:21:06.623032+00:00",
  "indices": {
    "SP500": {
      "symbol": "SPY",
      "price": 740.77,
      "change_percent": 0.35
    },
    "NASDAQ": {
      "symbol": "QQQ",
      "price": 713.59,
      "change_percent": 0.9
    },
    "GOLD": {
      "symbol": "GLD",
      "price": 431.52,
      "change_percent": -0.33
    }
  },
  "crypto": {
    "BITCOIN": {
      "price": 81030,
      "change_pct": 0.18784069559618302
    },
    "ETHEREUM": {
      "price": 2302.78,
      "change_pct": 0.7052736932383533
    },
    "SOLANA": {
      "price": 95.15,
      "change_pct": -0.46766235466739736
    }
  },
  "status": "ok",
  "errors": []
}