{
  "timestamp": "2026-05-11T14:15:23.283585+00:00",
  "indices": {
    "SP500": {
      "symbol": "SPY",
      "price": 738.99,
      "change_percent": 0.19
    },
    "NASDAQ": {
      "symbol": "QQQ",
      "price": 712.52,
      "change_percent": 0.18
    },
    "GOLD": {
      "symbol": "GLD",
      "price": 434.43,
      "change_percent": 0.15
    }
  },
  "crypto": {
    "BITCOIN": {
      "price": 81111,
      "change_pct": 0.2008131736840974
    },
    "ETHEREUM": {
      "price": 2325.54,
      "change_pct": -0.1452438592204495
    },
    "SOLANA": {
      "price": 95.57,
      "change_pct": 1.8186421340265588
    }
  },
  "status": "ok",
  "errors": []
}