{
  "timestamp": "2026-05-10T00:15:28.122229+00:00",
  "indices": {
    "SP500": {
      "symbol": "SPY",
      "price": 737.62,
      "change_percent": 0.83
    },
    "NASDAQ": {
      "symbol": "QQQ",
      "price": 711.23,
      "change_percent": 2.34
    },
    "GOLD": {
      "symbol": "GLD",
      "price": 433.77,
      "change_percent": 0.48
    }
  },
  "crypto": {
    "BITCOIN": {
      "price": 80703,
      "change_pct": 0.688087217084373
    },
    "ETHEREUM": {
      "price": 2327.03,
      "change_pct": 0.9251131422024528
    },
    "SOLANA": {
      "price": 93.12,
      "change_pct": 1.1782205494838218
    }
  },
  "status": "ok",
  "errors": []
}