{
  "timestamp": "2026-05-17T16:31:02.354985+00:00",
  "indices": {
    "SP500": {
      "symbol": "SPY",
      "price": 739.17,
      "change_percent": -1.2
    },
    "NASDAQ": {
      "symbol": "QQQ",
      "price": 708.93,
      "change_percent": -1.51
    },
    "GOLD": {
      "symbol": "GLD",
      "price": 417.29,
      "change_percent": -2.32
    }
  },
  "crypto": {
    "BITCOIN": {
      "price": 78100,
      "change_pct": -0.17959818248896112
    },
    "ETHEREUM": {
      "price": 2185.7,
      "change_pct": 0.4727787027054943
    },
    "SOLANA": {
      "price": 86.53,
      "change_pct": -0.0860828179503454
    }
  },
  "status": "ok",
  "errors": []
}