{
  "timestamp": "2026-05-14T23:25:06.144987+00:00",
  "indices": {
    "SP500": {
      "symbol": "SPY",
      "price": 748.06,
      "change_percent": -0.01
    },
    "NASDAQ": {
      "symbol": "QQQ",
      "price": 720.31,
      "change_percent": 0.07
    },
    "GOLD": {
      "symbol": "GLD",
      "price": 427.35,
      "change_percent": 0.03
    }
  },
  "crypto": {
    "BITCOIN": {
      "price": 81185,
      "change_pct": 2.3030444989682386
    },
    "ETHEREUM": {
      "price": 2291.3,
      "change_pct": 1.4522544195403482
    },
    "SOLANA": {
      "price": 92.34,
      "change_pct": 1.2579634612286754
    }
  },
  "status": "ok",
  "errors": []
}