{
  "timestamp": "2026-05-10T19:30:36.449076+00:00",
  "indices": {
    "SP500": {
      "symbol": "SPY",
      "price": 737.62,
      "change_percent": 0.83
    },
    "NASDAQ": {
      "symbol": "QQQ",
      "price": 711.23,
      "change_percent": 2.34
    },
    "GOLD": {
      "symbol": "GLD",
      "price": 433.77,
      "change_percent": 0.48
    }
  },
  "crypto": {
    "BITCOIN": {
      "price": 81457,
      "change_pct": 0.8200952882324805
    },
    "ETHEREUM": {
      "price": 2365.22,
      "change_pct": 1.5897856904964245
    },
    "SOLANA": {
      "price": 96.78,
      "change_pct": 3.724908973836358
    }
  },
  "status": "ok",
  "errors": []
}