{
  "timestamp": "2026-05-19T08:41:17.292014+00:00",
  "indices": {
    "SP500": {
      "symbol": "SPY",
      "price": 737.43,
      "change_percent": -0.16
    },
    "NASDAQ": {
      "symbol": "QQQ",
      "price": 703.75,
      "change_percent": -0.3
    },
    "GOLD": {
      "symbol": "GLD",
      "price": 417.09,
      "change_percent": -0.32
    }
  },
  "crypto": {
    "BITCOIN": {
      "price": 77069,
      "change_pct": 0.2173517250746913
    },
    "ETHEREUM": {
      "price": 2135.11,
      "change_pct": 0.8396033199003475
    },
    "SOLANA": {
      "price": 85.29,
      "change_pct": 0.7529685082746231
    }
  },
  "status": "ok",
  "errors": []
}