{
  "timestamp": "2026-05-10T20:40:13.780369+00:00",
  "indices": {
    "SP500": {
      "symbol": "SPY",
      "price": 737.62,
      "change_percent": 0.83
    },
    "NASDAQ": {
      "symbol": "QQQ",
      "price": 711.23,
      "change_percent": 2.34
    },
    "GOLD": {
      "symbol": "GLD",
      "price": 433.77,
      "change_percent": 0.48
    }
  },
  "crypto": {
    "BITCOIN": {
      "price": 81043,
      "change_pct": 0.33698128389833576
    },
    "ETHEREUM": {
      "price": 2345.87,
      "change_pct": 0.7553679015682498
    },
    "SOLANA": {
      "price": 95.41,
      "change_pct": 2.3621427935281156
    }
  },
  "status": "ok",
  "errors": []
}