{
  "timestamp": "2026-05-04T02:51:00.195019+00:00",
  "indices": {
    "SP500": {
      "symbol": "SPY",
      "price": 720.65,
      "change_percent": 0.28
    },
    "NASDAQ": {
      "symbol": "QQQ",
      "price": 674.15,
      "change_percent": 0.96
    },
    "GOLD": {
      "symbol": "GLD",
      "price": 423.18,
      "change_percent": -0.11
    }
  },
  "crypto": {
    "BITCOIN": {
      "price": 80044,
      "change_pct": 2.4490143128551116
    },
    "ETHEREUM": {
      "price": 2379.59,
      "change_pct": 3.367980986125437
    },
    "SOLANA": {
      "price": 85.41,
      "change_pct": 2.106235640325358
    }
  },
  "status": "ok",
  "errors": []
}