{
  "timestamp": "2026-05-17T21:05:20.163590+00:00",
  "indices": {
    "SP500": {
      "symbol": "SPY",
      "price": 739.17,
      "change_percent": -1.2
    },
    "NASDAQ": {
      "symbol": "QQQ",
      "price": 708.93,
      "change_percent": -1.51
    },
    "GOLD": {
      "symbol": "GLD",
      "price": 417.29,
      "change_percent": -2.32
    }
  },
  "crypto": {
    "BITCOIN": {
      "price": 78208,
      "change_pct": -0.03598902601705642
    },
    "ETHEREUM": {
      "price": 2186.76,
      "change_pct": 0.2533202455297833
    },
    "SOLANA": {
      "price": 86.61,
      "change_pct": -0.07663434596976476
    }
  },
  "status": "ok",
  "errors": []
}