{
  "timestamp": "2026-05-04T06:20:43.279793+00:00",
  "indices": {
    "SP500": {
      "symbol": "SPY",
      "price": 720.65,
      "change_percent": 0.28
    },
    "NASDAQ": {
      "symbol": "QQQ",
      "price": 674.15,
      "change_percent": 0.96
    },
    "GOLD": {
      "symbol": "GLD",
      "price": 423.18,
      "change_percent": -0.11
    }
  },
  "crypto": {
    "BITCOIN": {
      "price": 79815,
      "change_pct": 2.1730185871490257
    },
    "ETHEREUM": {
      "price": 2368.62,
      "change_pct": 2.9457916919530884
    },
    "SOLANA": {
      "price": 85.19,
      "change_pct": 1.8489981999946952
    }
  },
  "status": "ok",
  "errors": []
}