{
  "timestamp": "2026-05-19T06:11:03.352133+00:00",
  "indices": {
    "SP500": {
      "symbol": "SPY",
      "price": 738.65,
      "change_percent": -0.07
    },
    "NASDAQ": {
      "symbol": "QQQ",
      "price": 705.88,
      "change_percent": -0.43
    },
    "GOLD": {
      "symbol": "GLD",
      "price": 418.43,
      "change_percent": 0.27
    }
  },
  "crypto": {
    "BITCOIN": {
      "price": 76889,
      "change_pct": 0.24301696242100482
    },
    "ETHEREUM": {
      "price": 2132.6,
      "change_pct": 0.8821434424625259
    },
    "SOLANA": {
      "price": 85.12,
      "change_pct": 0.6577528095884853
    }
  },
  "status": "ok",
  "errors": []
}