{
  "timestamp": "2026-05-14T21:01:03.122932+00:00",
  "indices": {
    "SP500": {
      "symbol": "SPY",
      "price": 747.75,
      "change_percent": -0.06
    },
    "NASDAQ": {
      "symbol": "QQQ",
      "price": 719.66,
      "change_percent": -0.02
    },
    "GOLD": {
      "symbol": "GLD",
      "price": 426.99,
      "change_percent": -0.06
    }
  },
  "crypto": {
    "BITCOIN": {
      "price": 81372,
      "change_pct": 2.1898963211170357
    },
    "ETHEREUM": {
      "price": 2297.92,
      "change_pct": 1.6522626596590453
    },
    "SOLANA": {
      "price": 92.73,
      "change_pct": 1.712753344736283
    }
  },
  "status": "ok",
  "errors": []
}