{
  "timestamp": "2026-05-11T18:00:56.963997+00:00",
  "indices": {
    "SP500": {
      "symbol": "SPY",
      "price": 740.33,
      "change_percent": 0.37
    },
    "NASDAQ": {
      "symbol": "QQQ",
      "price": 713.81,
      "change_percent": 0.36
    },
    "GOLD": {
      "symbol": "GLD",
      "price": 433.78,
      "change_percent": 0.0
    }
  },
  "crypto": {
    "BITCOIN": {
      "price": 81896,
      "change_pct": 0.5482628478082778
    },
    "ETHEREUM": {
      "price": 2335.87,
      "change_pct": -1.2118800277923678
    },
    "SOLANA": {
      "price": 97.77,
      "change_pct": 1.5807272054310582
    }
  },
  "status": "ok",
  "errors": []
}