{
  "timestamp": "2026-05-05T20:25:50.686973+00:00",
  "indices": {
    "SP500": {
      "symbol": "SPY",
      "price": 724.75,
      "change_percent": 0.14
    },
    "NASDAQ": {
      "symbol": "QQQ",
      "price": 683.42,
      "change_percent": 0.28
    },
    "GOLD": {
      "symbol": "GLD",
      "price": 418.3,
      "change_percent": 0.02
    }
  },
  "crypto": {
    "BITCOIN": {
      "price": 81601,
      "change_pct": 1.9821913428034295
    },
    "ETHEREUM": {
      "price": 2382.01,
      "change_pct": 1.2505849010161603
    },
    "SOLANA": {
      "price": 86.61,
      "change_pct": 2.853945304753882
    }
  },
  "status": "ok",
  "errors": []
}