{
  "timestamp": "2026-05-16T17:21:00.461355+00:00",
  "indices": {
    "SP500": {
      "symbol": "SPY",
      "price": 739.17,
      "change_percent": -1.2
    },
    "NASDAQ": {
      "symbol": "QQQ",
      "price": 708.93,
      "change_percent": -1.51
    },
    "GOLD": {
      "symbol": "GLD",
      "price": 417.29,
      "change_percent": -2.32
    }
  },
  "crypto": {
    "BITCOIN": {
      "price": 78216,
      "change_pct": -1.345196970351053
    },
    "ETHEREUM": {
      "price": 2175.93,
      "change_pct": -2.3029018518372157
    },
    "SOLANA": {
      "price": 86.66,
      "change_pct": -3.2939281266937495
    }
  },
  "status": "ok",
  "errors": []
}