{
  "timestamp": "2026-05-12T23:40:34.627189+00:00",
  "indices": {
    "SP500": {
      "symbol": "SPY",
      "price": 737.1,
      "change_percent": -0.14
    },
    "NASDAQ": {
      "symbol": "QQQ",
      "price": 705.46,
      "change_percent": -0.25
    },
    "GOLD": {
      "symbol": "GLD",
      "price": 433.41,
      "change_percent": 0.11
    }
  },
  "crypto": {
    "BITCOIN": {
      "price": 80491,
      "change_pct": -1.493527184100249
    },
    "ETHEREUM": {
      "price": 2277.88,
      "change_pct": -2.6100386918219773
    },
    "SOLANA": {
      "price": 94.46,
      "change_pct": -2.9084600195793437
    }
  },
  "status": "ok",
  "errors": []
}