{
  "timestamp": "2026-05-20T04:50:45.256690+00:00",
  "indices": {
    "SP500": {
      "symbol": "SPY",
      "price": 733.73,
      "change_percent": -0.67
    },
    "NASDAQ": {
      "symbol": "QQQ",
      "price": 701.53,
      "change_percent": -0.62
    },
    "GOLD": {
      "symbol": "GLD",
      "price": 411.5,
      "change_percent": -1.66
    }
  },
  "crypto": {
    "BITCOIN": {
      "price": 76691,
      "change_pct": -0.22186911058903355
    },
    "ETHEREUM": {
      "price": 2109.33,
      "change_pct": -1.109873656227446
    },
    "SOLANA": {
      "price": 83.98,
      "change_pct": -1.3592723304346415
    }
  },
  "status": "ok",
  "errors": []
}