{
  "timestamp": "2026-05-10T04:00:20.222087+00:00",
  "indices": {
    "SP500": {
      "symbol": "SPY",
      "price": 737.62,
      "change_percent": 0.83
    },
    "NASDAQ": {
      "symbol": "QQQ",
      "price": 711.23,
      "change_percent": 2.34
    },
    "GOLD": {
      "symbol": "GLD",
      "price": 433.77,
      "change_percent": 0.48
    }
  },
  "crypto": {
    "BITCOIN": {
      "price": 80784,
      "change_pct": 0.44496717195797464
    },
    "ETHEREUM": {
      "price": 2327.68,
      "change_pct": 0.4599342218701082
    },
    "SOLANA": {
      "price": 93.42,
      "change_pct": -0.2617398744242904
    }
  },
  "status": "ok",
  "errors": []
}