{
  "timestamp": "2026-05-06T05:55:39.213086+00:00",
  "indices": {
    "SP500": {
      "symbol": "SPY",
      "price": 723.77,
      "change_percent": 0.8
    },
    "NASDAQ": {
      "symbol": "QQQ",
      "price": 681.61,
      "change_percent": 1.3
    },
    "GOLD": {
      "symbol": "GLD",
      "price": 418.27,
      "change_percent": 0.86
    }
  },
  "crypto": {
    "BITCOIN": {
      "price": 81218,
      "change_pct": 0.2861278677727687
    },
    "ETHEREUM": {
      "price": 2361.81,
      "change_pct": -0.7642047744435208
    },
    "SOLANA": {
      "price": 87.29,
      "change_pct": 2.8115600079074157
    }
  },
  "status": "ok",
  "errors": []
}